photosynthetic/Cloud.py
photosynthetic/Colors.py
photosynthetic/Debug.py
photosynthetic/Histogram.py
photosynthetic/Palette.py
photosynthetic/PaletteImage.py
photosynthetic/__init__.py
photosynthetic/colors.json
photosynthetic-0.0.16.dist-info/LICENSE
photosynthetic-0.0.16.dist-info/METADATA
photosynthetic-0.0.16.dist-info/WHEEL
photosynthetic-0.0.16.dist-info/top_level.txt
photosynthetic-0.0.16.dist-info/RECORD
