Metadata-Version: 2.1
Name: photosynthetic
Version: 0.0.16
Summary: Perform color and palette analysis on images
Home-page: https://gitlab.com/thinkhuman-public/photosynthetic
Author: valeness
Author-email: james@thinkhuman.co
License: UNKNOWN
Platform: UNKNOWN
Classifier: Programming Language :: Python :: 3
Classifier: License :: OSI Approved :: GNU General Public License v3 (GPLv3)
Classifier: Operating System :: OS Independent
Requires-Python: >=3.6
License-File: LICENSE
Requires-Dist: numpy (~=1.22)
Requires-Dist: pillow (~=8.0)
Requires-Dist: scikit-image (~=0.17.2)
Requires-Dist: matplotlib (~=3.3.2)
